Multicycle/mipsmultimem.v
//------------------------------------------------
// mipsmemsingle.sv
// Updated to SystemVerilog - Harris Harris version
// External memories used by MIPS single-cycle
// processor
//------------------------------------------------

module mem(input          clk, we, 
            input   [31:0] a, wd, 
            output  [31:0] rd);

  reg [31:0] RAM[0:63];
  initial
    begin
      $readmemh("memfile.dat",RAM); // initialize memory
    end
 
  assign rd = RAM[a[31:2]]; // word aligned

  always @(posedge clk) begin
    if (we)
      RAM[a[31:2]] <= wd;
  end
endmodule

Singlecycle/LOGIC.v
module Logic (A,B,AluOp,Logic);
  input [31:0] A,B;
  input [3:0] AluOp;
  output [31:0] Logic;

  assign Logic = AluOp[1]? AluOp[0]? ~(A | B) 
                                      : 
                                     (A ^ B) // cuando el Alu[1] es 1 haremos un xor o un nor 
                            :   
                           AluOp[0]? (A | B) 
                                      : 
                                     (A & B); /// cuando el Alu[0] es 0 haremos un and o un Or

endmodule

Multicycle/ARITMETIC.v
module Aritmetic (AluOp,A,B,Aritm);
  input [3:0] AluOp;
  input [31:0] A,B;
  output [31:0] Aritm;
  wire [31:0] mux1,adder,extend,mux2;

// mux b con ~b depedende del AluOp[1] determina si es suma o resta 
  assign mux1 = AluOp[1]? ~B : B;

// suma el AluOp[1] con A y B si es suma y con ~B si es resta
  assign adder = AluOp[1] + A + mux1;

// sacamos el bit mas significativo del adder y hacer el extend 
  assign extend = adder[31] + 32'b0;  // = 0 v 1 se llena solo al ser de 32 bits if 0: 000....00000 ^ 1: 0000000... 01

// mux para determinar si se pide un slt o no y asu vez dar la salida del bloque de AritmeticOp
  assign Aritm = AluOp[3]? extend : adder;
endmodule

Multicycle/ALU.v
module Alu (A,B,AluOp,Result,zero);
  input [31:0] A,B;
  input [3:0] AluOp;
  output [31:0] Result;
  output zero;
  wire [31:0] Logic,Aritm;

  //Modulo Aritmetic aqui se hace el add , sub y slt 
  Aritmetic Arit (.A(A),
               .B(B),
               .AluOp(AluOp),
               .Aritm(Aritm)
               );

  //Modulo Logic aqui se hace el and, or, nor, xor 
  Logic Log (.A(A),
           .B(B),
           .AluOp(AluOp),
           .Logic(Logic)
           );

  // El Result depende de del segundo bit mas significativo si es 0 sabemos que ejecutaremos el modulo Aritmetic pero sino ejecutaremos el modulo Logic 
  assign Result = AluOp[2]? Logic : Aritm;
  
  //El zero se prende cuando todos los digitos del result son ceros y para asegurarnos de eso hacemos un or entre todos los bits del Result 
  //se niega porque el or entre todos los bits del Result si todos son ceros seria 0 y queremos q la salida sea 1 .
  assign zero = ~(| Result);

endmodule

Multicycle/mipsmulti.v
//-------------------------------------------------------
// mipsmulti.sv
// From David_Harris and Sarah_Harris book design
// Multicycle MIPS processor
//------------------------------------------------

module mips(input          clk, reset,
            output  [31:0] adr, writedata,
            output         memwrite,
            input   [31:0] readdata);

  wire        zero, pcen, irwrite, regwrite,
               alusrca, iord, memtoreg, regdst;
  wire [1:0]  alusrcb, pcsrc;
  wire [3:0]  alucontrol;
  wire [5:0]  op, funct;

  controller c(clk, reset, op, funct, zero,
               pcen, memwrite, irwrite, regwrite,
               alusrca, iord, memtoreg, regdst, 
               alusrcb, pcsrc, alucontrol);
  datapath dp(clk, reset, 
              pcen, irwrite, regwrite,
              alusrca, iord, memtoreg, regdst,
              alusrcb, pcsrc, alucontrol,
              op, funct, zero,
              adr, writedata, readdata);
endmodule

module controller(input         clk, reset,
                  input   [5:0] op, funct,
                  input         zero,
                  output        pcen, memwrite, irwrite, regwrite,
                  output        alusrca, iord, memtoreg, regdst,
                  output  [1:0] alusrcb, pcsrc,
                  output  [3:0] alucontrol);

  wire [1:0] aluop;
  wire branch, pcwrite;

  // Main Decoder and ALU Decoder subunits.
  maindec md(clk, reset, op,
             pcwrite, memwrite, irwrite, regwrite,
             alusrca, branch, iord, memtoreg, regdst, 
             alusrcb, pcsrc, aluop);
  aludec  ad(funct, aluop, alucontrol);

  // ADD CODE HERE
  // Add combinational logic (i.e. an assign statement) 
  // to produce the PCEn signal (pcen) from the branch, 
  // zero, and pcwrite signals
  assign pcen = pcwrite || (branch && zero);
 
endmodule

module maindec(input         clk, reset, 
               input   [5:0] op, 
               output        pcwrite, memwrite, irwrite, regwrite,
               output        alusrca, branch, iord, memtoreg, regdst,
               output  [1:0] alusrcb, pcsrc,
               output  [1:0] aluop);

  parameter   FETCH   = 4'b0000; // State 0
  parameter   DECODE  = 4'b0001; // State 1
  parameter   MEMADR  = 4'b0010;	// State 2
  parameter   MEMRD   = 4'b0011;	// State 3
  parameter   MEMWB   = 4'b0100;	// State 4
  parameter   MEMWR   = 4'b0101;	// State 5
  parameter   RTYPEEX = 4'b0110;	// State 6
  parameter   RTYPEWB = 4'b0111;	// State 7
  parameter   BEQEX   = 4'b1000;	// State 8
  parameter   ADDIEX  = 4'b1001;	// State 9
  parameter   ADDIWB  = 4'b1010;	// state 10
  parameter   JEX     = 4'b1011;	// State 11

  parameter   LW      = 6'b100011;	// Opcode for lw
  parameter   SW      = 6'b101011;	// Opcode for sw
  parameter   RTYPE   = 6'b000000;	// Opcode for R-type
  parameter   BEQ     = 6'b000100;	// Ospcode for beq
  parameter   ADDI    = 6'b001000;	// Opcode for addi
  parameter   J       = 6'b000010;	// Opcode for j

  reg [3:0]  state, nextstate;
  reg [14:0] controls;

  // state register
  always @(posedge clk or posedge reset) begin			
    if(reset) state <= FETCH;
    else state <= nextstate;
  end
  // ADD CODE HERE
  // Finish entering the next state logic below.  We've completed the first 
  // two states, FETCH and DECODE, for you.

  // next state logic
  always@(*)
    case(state)
      FETCH:   nextstate <= DECODE;
      DECODE:  case(op)
                 LW:      	nextstate <= MEMADR;
                 SW:      	nextstate <= MEMADR;
                 RTYPE:   	nextstate <= RTYPEEX;
                 BEQ:     	nextstate <= BEQEX;
                 ADDI:    	nextstate <= ADDIEX;
                 J:       	nextstate <= JEX;
                 default: 	nextstate <= 4'bx; // should never happen
               endcase
 		// Add code here
      MEMADR:	case(op)
      		  LW:	   	nextstate <= MEMRD;
      		  SW:	   	nextstate <= MEMWR;
      		  default:	nextstate <= 4'bx;
      		endcase
      MEMRD:	nextstate <= MEMWB;
      MEMWB: 	nextstate <= FETCH;
      MEMWR: 	nextstate <= FETCH;
      RTYPEEX: 	nextstate <= RTYPEWB;
      RTYPEWB: 	nextstate <= FETCH;
      BEQEX:   	nextstate <= FETCH;
      ADDIEX:  	nextstate <= ADDIWB;
      ADDIWB:  	nextstate <= FETCH;
      JEX:     	nextstate <= FETCH;
      default: 	nextstate <= 4'bx; // should never happen
    endcase

// output logic
  assign {pcwrite, memwrite, irwrite, regwrite, 
          alusrca, branch, iord, memtoreg, regdst,
          alusrcb, pcsrc, aluop} = controls;

  // ADD CODE HERE
  // Finish entering the output logic below.  We've entered the
  // output logic for the first two states, S0 and S1, for you.
  always @(*)
    case(state)
      FETCH:   controls <= 15'h5010;
      DECODE:  controls <= 15'h0030;
      MEMADR:  controls <= 15'h0420;
      MEMRD:   controls <= 15'h0100;
      MEMWB:   controls <= 15'h0880;
      MEMWR:   controls <= 15'h2100;
      RTYPEEX: controls <= 15'h0402; 
      RTYPEWB: controls <= 15'h0840;
      BEQEX:   controls <= 15'h0605;
      ADDIEX:  controls <= 15'h0420;
      ADDIWB:  controls <= 15'h0800;
      JEX:     controls <= 15'h4008;
      default: controls <= 15'hxxxx; // should never happen
    endcase
endmodule


  // ADD CODE HERE
  // Complete the design for the ALU Decoder.
  // Your design goes here.  Remember that this is a combinational 
  // module. 

  // Remember that you may also reuse any code from previous labs.
module aludec(input   [5:0] funct,
              input   [1:0] aluop,
              output reg [3:0] alucontrol);

  always @* begin
    case(aluop)
      2'b00: alucontrol <= 4'b0000;  // add
      2'b01: alucontrol <= 4'b0010;  // sub
      2'b11: alucontrol <= 4'b0101;  // or

      default: case(funct)          // RTYPE
          6'b100000: alucontrol <= 4'b0000; // ADD
          6'b100010: alucontrol <= 4'b0010; // SUB
          6'b100100: alucontrol <= 4'b0100; // AND
          6'b100101: alucontrol <= 4'b0101; // OR
          6'b100111: alucontrol <= 4'b0111; // NOR
          6'b100110: alucontrol <= 4'b0110; // XOR
          6'b101010: alucontrol <= 4'b1010; // SLT
          default:   alucontrol <= 4'bxxxx; // ???
      endcase
    endcase
  end 
endmodule
// The datapath unit is a structural verilog module.  That is,
// it is composed of instances of its sub-modules.  For example,
// the instruction register is instantiated as a 32-bit flopenr.
// The other submodules are likewise instantiated.

module datapath(input          clk, reset,
                input          pcen, irwrite, regwrite,
                input          alusrca, iord, memtoreg, regdst,
                input   [1:0]  alusrcb, pcsrc, 
                input   [3:0]  alucontrol,
                output  [5:0]  op, funct,
                output         zero,
                output  [31:0] adr, writedata, 
                input   [31:0] readdata);

  // Below are the internal signals of the datapath module.

  wire [4:0]  writereg;
  wire [31:0] pcnext, pc;
  wire [31:0] instr, data, srca, srcb;

  wire [31:0] A ,B;
  wire [31:0] aluresult, aluout;
  wire [31:0] signimm;   // the sign-extended immediate
  wire [31:0] signimmsh;	// the sign-extended immediate shifted left by 2
  wire [31:0] wd3, rd1, rd2;
  wire [31:0] pcjump;

  // op and funct fields to controller
  assign op = instr[31:26];
  assign funct = instr[5:0];
  assign writedata=B;
  assign pcjump={pc[31:28],{instr[25:0],2'b00}};
  // Your datapath hardware goes below.  Instantiate each of the submodules
  // that you need.  Remember that alu's, mux's and various other 
  // versions of parameterizable modules are available in mipsparts.sv
  // from Lab 9. You'll likely want to include this verilog file in your
  // simulation.
  flopenr #(32)	        pcreg(clk, reset, pcen, pcnext, pc);
  mux2 #(32)            muxfetch(pc, aluout, iord, adr);

  flopenr #(32)	        intrdecode(clk, reset, irwrite, readdata, instr);
  flopr #(32)		rdata(clk, reset, readdata, data);
  mux2 #(5)             muxrt(instr[20:16], instr[15:11], regdst, writereg);
  mux2 #(32)            wdmux(aluout, data, memtoreg, wd3);

  regfile               rf(clk, regwrite, instr[25:21], instr[20:16], writereg, wd3, rd1, rd2);
  signext               sign(instr[15:0], signimm);

  floprx2 #(32)         readata12(clk,reset,rd1,rd2,A,B);
  //assign                writedata=B;

  sl2                   sll2(signimm, signimmsh);
  mux4 #(32)            mux4x1(B, 32'b100, signimm, signimmsh, alusrcb, srcb);
  mux2 #(32)            muxsrca(pc, A, alusrca, srca);
  
  Alu                   alu(.A(srca), .B(srcb), .AluOp(alucontrol), .Result(aluresult), .zero(zero));

  //assign                pcjump={pc[31:28],pc[25:0],2'b00};
  flopr #(32)		alures(clk, reset, aluresult, aluout);

  mux3 #(32)		mux3x1(aluresult, aluout, pcjump, pcsrc, pcnext);
  
  // We've included parameterizable 3:1 and 4:1 muxes below for your use.

  // Remember to give your instantiated modules applicable names
  // such as pcreg (PC register), wdmux (Write Data Mux), etc.
  // so it's easier to understand.

  // ADD CODE HERE

  // datapath
  
endmodule

Multicycle/mipsmultitop.v
//------------------------------------------------
// topmulti.sv
// As proposed by Prof. David Harris
// and unified memory
//------------------------------------------------

module top(input          clk, reset, 
           output  [31:0] writedata, adr, 
           output         memwrite);

  wire [31:0] readdata;
  
  // microprocessor (control & datapath)
  mips mips(clk, reset, adr, writedata, memwrite, readdata);

  // memory 
  mem mem(clk, memwrite, adr, writedata, readdata);

endmodule

Multicycle/mipstest.v
module testbench();
  reg clk;
  reg reset;

  wire [31:0]writedata, adr;
  wire memwrite;

  // instantiate device to be tested
  top dut(clk, reset, writedata, adr, memwrite);
  //dut dut(clk, reset, writedata, dataadr, memwrite);

  // initialize test
  initial
    begin
      reset <= 1; 
      #22; 
      reset <= 0;
    end

  // generate clock to sequence tests
  always
    begin
      clk <= 1; 
      #5; 
      clk <= 0; 
      #5;
    end

  // check that 7 gets written to address 84
  always@(negedge clk)
    begin
      if(memwrite) begin
        if(adr === 84 & writedata === 7) begin
          $display("Simulation succeeded");
          $finish;
        end else if (adr !== 80) begin
          $display("Simulation failed");
          $finish;
        end
      end
    end

    initial begin
        $dumpfile("testbench.vcd");
        $dumpvars; 
    end

endmodule

Multicycle/mipsmultiparts.v
//------------------------------------------------
// mipsparts.sv
// Updated to SystemVerilog - Harris Harris version
// Components used in MIPS processor
//------------------------------------------------

module regfile(input          clk,
               input          we3,
               input   [4:0]  ra1, ra2, wa3,
               input   [31:0] wd3,
               output  [31:0] rd1, rd2);

  reg [31:0] rf[31:0];

  // three ported register file
  // read two ports combinationally
  // write third port on rising edge of clock
  // register 0 hardwired to 0


  always @(posedge clk) begin
    if (we3) rf[wa3] <= wd3;
  end
  assign rd1 = (ra1 != 0) ? rf[ra1] : 0;
  assign rd2 = (ra2 != 0) ? rf[ra2] : 0;
endmodule

module adder(input   [31:0] a, b,
             output  [31:0] y);

  assign y = a + b;
endmodule

module sl2(input   [31:0] a,
           output  [31:0] y);

  // shift left by 2
  assign y = {a[29:0], 2'b00};
endmodule
module signext(input   [15:0] a,
               //input   alusrc,
               //input   [3:0]alucontrol,
               output  [31:0] y);
//  assign y = (alucontrol== 4'b0101 && alusrc == 1'b1 )? {{16{1'b0}},a}:{{16{a[15]}}, a};
  assign y = {{16{a[15]}}, a};
endmodule

module flopr #(parameter WIDTH = 8)
              (input               clk, reset,
               input   [WIDTH-1:0] d,
               output reg [WIDTH-1:0] q);

  always @(posedge clk, posedge reset) begin
    if (reset) q <= 0;
    else       q <= d;
  end
endmodule

module floprx2 #(parameter WIDTH = 8)
              (input               clk, reset,
               input   [WIDTH-1:0] d0,d1,
               output reg [WIDTH-1:0] q0,q1); 

  always @(posedge clk, posedge reset) begin
    if (reset) begin
      q0 <= 0;
      q1 <= 0;
    end
    else begin       
      q0 <= d0;
      q1 <= d1;
    end
  end 
endmodule

module flopenr #(parameter WIDTH = 8)
                (input               clk, reset,
                 input               en,
                 input   [WIDTH-1:0] d,
                 output reg [WIDTH-1:0] q);

  always @(posedge clk, posedge reset) begin
    if      (reset) q <= 0;
    else if (en)    q <= d;
  end
endmodule

module mux2 #(parameter WIDTH = 8)
             (input   [WIDTH-1:0] d0, d1,
              input               s,
              output  [WIDTH-1:0] y);

  assign y = s ? d1 : d0;
endmodule

module mux3 #(parameter WIDTH = 8)
             (input   [WIDTH-1:0] d0, d1, d2, 
              input   [1:0]       s,  
              output  [WIDTH-1:0] y); 

  assign #1 y = s[1] ? d2 : (s[0] ? d1 : d0); 
endmodule

module mux4 #(parameter WIDTH = 8)
             (input   [WIDTH-1:0] d0, d1, d2, d3, 
              input   [1:0]       s,  
              output reg [WIDTH-1:0] y); 

   always @(*) begin
      case(s)
         2'b00: y <= d0; 
         2'b01: y <= d1; 
         2'b10: y <= d2; 
         2'b11: y <= d3; 
      endcase
   end
endmodule

Multicycle/testbench.vcd
$date
	Wed Jul 22 11:51:57 2020
$end
$version
	Icarus Verilog
$end
$timescale
	1s
$end
$scope module adder $end
$var wire 32 ! a [31:0] $end
$var wire 32 " b [31:0] $end
$var wire 32 # y [31:0] $end
$upscope $end
$scope module testbench $end
$var wire 32 $ writedata [31:0] $end
$var wire 1 % memwrite $end
$var wire 32 & adr [31:0] $end
$var reg 1 ' clk $end
$var reg 1 ( reset $end
$scope module dut $end
$var wire 1 ' clk $end
$var wire 1 ( reset $end
$var wire 32 ) writedata [31:0] $end
$var wire 32 * readdata [31:0] $end
$var wire 1 % memwrite $end
$var wire 32 + adr [31:0] $end
$scope module mem $end
$var wire 1 ' clk $end
$var wire 32 , rd [31:0] $end
$var wire 1 % we $end
$var wire 32 - wd [31:0] $end
$var wire 32 . a [31:0] $end
$upscope $end
$scope module mips $end
$var wire 1 ' clk $end
$var wire 32 / readdata [31:0] $end
$var wire 1 ( reset $end
$var wire 1 0 zero $end
$var wire 32 1 writedata [31:0] $end
$var wire 1 2 regwrite $end
$var wire 1 3 regdst $end
$var wire 2 4 pcsrc [1:0] $end
$var wire 1 5 pcen $end
$var wire 6 6 op [5:0] $end
$var wire 1 % memwrite $end
$var wire 1 7 memtoreg $end
$var wire 1 8 irwrite $end
$var wire 1 9 iord $end
$var wire 6 : funct [5:0] $end
$var wire 2 ; alusrcb [1:0] $end
$var wire 1 < alusrca $end
$var wire 4 = alucontrol [3:0] $end
$var wire 32 > adr [31:0] $end
$scope module c $end
$var wire 1 ' clk $end
$var wire 1 5 pcen $end
$var wire 1 ( reset $end
$var wire 1 0 zero $end
$var wire 1 2 regwrite $end
$var wire 1 3 regdst $end
$var wire 1 ? pcwrite $end
$var wire 2 @ pcsrc [1:0] $end
$var wire 6 A op [5:0] $end
$var wire 1 % memwrite $end
$var wire 1 7 memtoreg $end
$var wire 1 8 irwrite $end
$var wire 1 9 iord $end
$var wire 6 B funct [5:0] $end
$var wire 1 C branch $end
$var wire 2 D alusrcb [1:0] $end
$var wire 1 < alusrca $end
$var wire 2 E aluop [1:0] $end
$var wire 4 F alucontrol [3:0] $end
$scope module ad $end
$var wire 6 G funct [5:0] $end
$var wire 2 H aluop [1:0] $end
$var reg 4 I alucontrol [3:0] $end
$upscope $end
$scope module md $end
$var wire 1 ' clk $end
$var wire 1 ( reset $end
$var wire 1 2 regwrite $end
$var wire 1 3 regdst $end
$var wire 1 ? pcwrite $end
$var wire 2 J pcsrc [1:0] $end
$var wire 6 K op [5:0] $end
$var wire 1 % memwrite $end
$var wire 1 7 memtoreg $end
$var wire 1 8 irwrite $end
$var wire 1 9 iord $end
$var wire 1 C branch $end
$var wire 2 L alusrcb [1:0] $end
$var wire 1 < alusrca $end
$var wire 2 M aluop [1:0] $end
$var reg 15 N controls [14:0] $end
$var reg 4 O nextstate [3:0] $end
$var reg 4 P state [3:0] $end
$upscope $end
$upscope $end
$scope module dp $end
$var wire 4 Q alucontrol [3:0] $end
$var wire 1 < alusrca $end
$var wire 2 R alusrcb [1:0] $end
$var wire 1 ' clk $end
$var wire 1 9 iord $end
$var wire 1 8 irwrite $end
$var wire 1 7 memtoreg $end
$var wire 1 5 pcen $end
$var wire 2 S pcsrc [1:0] $end
$var wire 32 T readdata [31:0] $end
$var wire 1 3 regdst $end
$var wire 1 2 regwrite $end
$var wire 1 ( reset $end
$var wire 32 U writedata [31:0] $end
$var wire 1 0 zero $end
$var wire 5 V writereg [4:0] $end
$var wire 32 W wd3 [31:0] $end
$var wire 32 X srcb [31:0] $end
$var wire 32 Y srca [31:0] $end
$var wire 32 Z signimmsh [31:0] $end
$var wire 32 [ signimm [31:0] $end
$var wire 32 \ rd2 [31:0] $end
$var wire 32 ] rd1 [31:0] $end
$var wire 32 ^ pcnext [31:0] $end
$var wire 32 _ pcjump [31:0] $end
$var wire 32 ` pc [31:0] $end
$var wire 6 a op [5:0] $end
$var wire 32 b instr [31:0] $end
$var wire 6 c funct [5:0] $end
$var wire 32 d data [31:0] $end
$var wire 32 e aluresult [31:0] $end
$var wire 32 f aluout [31:0] $end
$var wire 32 g adr [31:0] $end
$var wire 32 h B [31:0] $end
$var wire 32 i A [31:0] $end
$scope module alu $end
$var wire 4 j AluOp [3:0] $end
$var wire 1 0 zero $end
$var wire 32 k Result [31:0] $end
$var wire 32 l Logic [31:0] $end
$var wire 32 m B [31:0] $end
$var wire 32 n Aritm [31:0] $end
$var wire 32 o A [31:0] $end
$scope module Arit $end
$var wire 4 p AluOp [3:0] $end
$var wire 32 q mux1 [31:0] $end
$var wire 32 r extend [31:0] $end
$var wire 32 s adder [31:0] $end
$var wire 32 t B [31:0] $end
$var wire 32 u Aritm [31:0] $end
$var wire 32 v A [31:0] $end
$upscope $end
$scope module Log $end
$var wire 4 w AluOp [3:0] $end
$var wire 32 x Logic [31:0] $end
$var wire 32 y B [31:0] $end
$var wire 32 z A [31:0] $end
$upscope $end
$upscope $end
$scope module alures $end
$var wire 1 ' clk $end
$var wire 32 { d [31:0] $end
$var wire 1 ( reset $end
$var reg 32 | q [31:0] $end
$upscope $end
$scope module intrdecode $end
$var wire 1 ' clk $end
$var wire 32 } d [31:0] $end
$var wire 1 8 en $end
$var wire 1 ( reset $end
$var reg 32 ~ q [31:0] $end
$upscope $end
$scope module mux3x1 $end
$var wire 32 !" d0 [31:0] $end
$var wire 32 "" d1 [31:0] $end
$var wire 32 #" d2 [31:0] $end
$var wire 2 $" s [1:0] $end
$var wire 32 %" y [31:0] $end
$upscope $end
$scope module mux4x1 $end
$var wire 32 &" d1 [31:0] $end
$var wire 2 '" s [1:0] $end
$var wire 32 (" d3 [31:0] $end
$var wire 32 )" d2 [31:0] $end
$var wire 32 *" d0 [31:0] $end
$var reg 32 +" y [31:0] $end
$upscope $end
$scope module muxfetch $end
$var wire 32 ," d1 [31:0] $end
$var wire 1 9 s $end
$var wire 32 -" y [31:0] $end
$var wire 32 ." d0 [31:0] $end
$upscope $end
$scope module muxrt $end
$var wire 5 /" d0 [4:0] $end
$var wire 5 0" d1 [4:0] $end
$var wire 1 3 s $end
$var wire 5 1" y [4:0] $end
$upscope $end
$scope module muxsrca $end
$var wire 1 < s $end
$var wire 32 2" y [31:0] $end
$var wire 32 3" d1 [31:0] $end
$var wire 32 4" d0 [31:0] $end
$upscope $end
$scope module pcreg $end
$var wire 1 ' clk $end
$var wire 32 5" d [31:0] $end
$var wire 1 5 en $end
$var wire 1 ( reset $end
$var reg 32 6" q [31:0] $end
$upscope $end
$scope module rdata $end
$var wire 1 ' clk $end
$var wire 32 7" d [31:0] $end
$var wire 1 ( reset $end
$var reg 32 8" q [31:0] $end
$upscope $end
$scope module readata12 $end
$var wire 1 ' clk $end
$var wire 1 ( reset $end
$var wire 32 9" d1 [31:0] $end
$var wire 32 :" d0 [31:0] $end
$var reg 32 ;" q0 [31:0] $end
$var reg 32 <" q1 [31:0] $end
$upscope $end
$scope module rf $end
$var wire 1 ' clk $end
$var wire 5 =" ra1 [4:0] $end
$var wire 5 >" ra2 [4:0] $end
$var wire 5 ?" wa3 [4:0] $end
$var wire 1 2 we3 $end
$var wire 32 @" wd3 [31:0] $end
$var wire 32 A" rd2 [31:0] $end
$var wire 32 B" rd1 [31:0] $end
$upscope $end
$scope module sign $end
$var wire 16 C" a [15:0] $end
$var wire 32 D" y [31:0] $end
$upscope $end
$scope module sll2 $end
$var wire 32 E" a [31:0] $end
$var wire 32 F" y [31:0] $end
$upscope $end
$scope module wdmux $end
$var wire 32 G" d0 [31:0] $end
$var wire 32 H" d1 [31:0] $end
$var wire 1 7 s $end
$var wire 32 I" y [31:0] $end
$upscope $end
$upscope $end
$upscope $end
$upscope $end
$upscope $end
$enddefinitions $end
#0
$dumpvars
b0 I"
b0 H"
b0 G"
b0 F"
b0 E"
b0 D"
b0 C"
b0 B"
b0 A"
b0 @"
b0 ?"
b0 >"
b0 ="
b1 <"
b0 ;"
b0 :"
b0 9"
b0 8"
b100000000000100000000000000101 7"
b0 6"
bx 5"
b0 4"
b0 3"
b0 2"
b0 1"
b0 0"
b0 /"
b0 ."
b0 -"
b0 ,"
b100 +"
b1 *"
b0 )"
b0 ("
b1 '"
b100 &"
bx %"
b0 $"
b0 #"
b0 ""
b100 !"
b0 ~
b100000000000100000000000000101 }
b0 |
b100 {
b0 z
b100 y
b0 x
b0 w
b0 v
b100 u
b100 t
b100 s
b0 r
b100 q
b0 p
b0 o
b100 n
b100 m
b0 l
b100 k
b0 j
b0 i
b1 h
b0 g
b0 f
b100 e
b0 d
b0 c
b0 b
b0 a
b0 `
b0 _
bx ^
b0 ]
b0 \
b0 [
b0 Z
b0 Y
b100 X
b0 W
b0 V
b1 U
b100000000000100000000000000101 T
b0 S
b1 R
b0 Q
b0 P
b1 O
b101000000010000 N
b0 M
b1 L
b0 K
b0 J
b0 I
b0 H
b0 G
b0 F
b0 E
b1 D
0C
b0 B
b0 A
b0 @
1?
b0 >
b0 =
0<
b1 ;
b0 :
09
18
07
b0 6
15
b0 4
03
02
b1 1
00
b100000000000100000000000000101 /
b0 .
b1 -
b100000000000100000000000000101 ,
b0 +
b100000000000100000000000000101 *
b1 )
1(
1'
b0 &
0%
b1 $
bx #
bz "
bz !
$end
#1
b100 ^
b100 %"
b100 5"
#5
0'
#10
1'
#15
0'
#20
1'
#22
0(
#25
0'
#30
b10100 q
b10100 X
b10100 m
b10100 t
b10100 y
b10100 +"
05
0?
08
b11 ;
b11 D
b11 L
b11 R
b11 '"
b110000 N
b1001 O
b100 l
b100 x
b11000 e
b11000 k
b11000 {
b11000 !"
b10100 Z
b10100 ("
b10100 F"
bx \
bx 9"
bx A"
b10 V
b10 1"
b10 ?"
b11000 n
b11000 u
b100000000000110000000000001100 *
b100000000000110000000000001100 ,
b100000000000110000000000001100 /
b100000000000110000000000001100 T
b100000000000110000000000001100 }
b100000000000110000000000001100 7"
b100 W
b100 @"
b100 I"
b101 [
b101 )"
b101 D"
b101 E"
b101 C"
b10 >"
b10 /"
b10000000000000010100 _
b10000000000000010100 #"
b101 :
b101 B
b101 G
b101 c
b1000 6
b1000 A
b1000 K
b1000 a
b11000 s
b100 Y
b100 o
b100 v
b100 z
b100 2"
b100 &
b100 +
b100 .
b100 >
b100 g
b100 -"
b100 f
b100 |
b100 ""
b100 ,"
b100 G"
b0 $
b0 )
b0 -
b0 1
b0 U
b0 h
b0 *"
b0 <"
b100000000000100000000000000101 d
b100000000000100000000000000101 8"
b100000000000100000000000000101 H"
b100000000000100000000000000101 b
b100000000000100000000000000101 ~
b100 `
b100 ."
b100 4"
b100 6"
b1 P
1'
#31
b11000 ^
b11000 %"
b11000 5"
#35
0'
#40
b101 q
b101 X
b101 m
b101 t
b101 y
b101 +"
b0 l
b0 x
b101 e
b101 k
b101 {
b101 !"
b101 n
b101 u
b101 s
b0 Y
b0 o
b0 v
b0 z
b0 2"
1<
b10 ;
b10 D
b10 L
b10 R
b10 '"
b10000100000 N
b1010 O
b11000 W
b11000 @"
b11000 I"
b1001 P
b100000000000110000000000001100 d
b100000000000110000000000001100 8"
b100000000000110000000000001100 H"
bx $
bx )
bx -
bx 1
bx U
bx h
bx *"
bx <"
b11000 f
b11000 |
b11000 ""
b11000 ,"
b11000 G"
1'
#41
b101 ^
b101 %"
b101 5"
#45
0'
#50
x0
bx r
bx q
bx X
bx m
bx t
bx y
bx +"
b0x00 l
b0x00 x
bx e
bx k
bx {
bx !"
bx n
bx u
bx s
b100 Y
b100 o
b100 v
b100 z
b100 2"
12
0<
b0 ;
b0 D
b0 L
b0 R
b0 '"
b100000000000 N
b0 O
b101 W
b101 @"
b101 I"
b101 f
b101 |
b101 ""
b101 ,"
b101 G"
b1010 P
1'
#51
bx ^
bx %"
bx 5"
#55
0'
#60
00
b100 l
b100 x
b1000 e
b1000 k
b1000 {
b1000 !"
b0 r
b1000 n
b1000 u
b1000 s
b100 q
b100 X
b100 m
b100 t
b100 y
b100 +"
15
1?
18
02
b1 ;
b1 D
b1 L
b1 R
b1 '"
b101000000010000 N
b1 O
b101 \
b101 9"
b101 A"
bx W
bx @"
bx I"
b0 P
bx f
bx |
bx ""
bx ,"
bx G"
1'
#61
b1000 ^
b1000 %"
b1000 5"
#65
0'
#70
b110000 q
b110000 X
b110000 m
b110000 t
b110000 y
b110000 +"
05
0?
08
b11 ;
b11 D
b11 L
b11 R
b11 '"
b110000 N
b1001 O
b0 l
b0 x
b111000 e
b111000 k
b111000 {
b111000 !"
b110000 Z
b110000 ("
b110000 F"
bx \
bx 9"
bx A"
b11 V
b11 1"
b11 ?"
b111000 n
b111000 u
b100000011001111111111111110111 *
b100000011001111111111111110111 ,
b100000011001111111111111110111 /
b100000011001111111111111110111 T
b100000011001111111111111110111 }
b100000011001111111111111110111 7"
b1000 W
b1000 @"
b1000 I"
b1100 [
b1100 )"
b1100 D"
b1100 E"
b1100 C"
b11 >"
b11 /"
b11000000000000110000 _
b11000000000000110000 #"
b1100 :
b1100 B
b1100 G
b1100 c
b111000 s
b1000 Y
b1000 o
b1000 v
b1000 z
b1000 2"
b1000 &
b1000 +
b1000 .
b1000 >
b1000 g
b1000 -"
b1000 f
b1000 |
b1000 ""
b1000 ,"
b1000 G"
b101 $
b101 )
b101 -
b101 1
b101 U
b101 h
b101 *"
b101 <"
b100000000000110000000000001100 b
b100000000000110000000000001100 ~
b1000 `
b1000 ."
b1000 4"
b1000 6"
b1 P
1'
#71
b111000 ^
b111000 %"
b111000 5"
#75
0'
#80
b1100 q
b1100 X
b1100 m
b1100 t
b1100 y
b1100 +"
b1100 e
b1100 k
b1100 {
b1100 !"
b1100 n
b1100 u
b1100 s
b0 Y
b0 o
b0 v
b0 z
b0 2"
1<
b10 ;
b10 D
b10 L
b10 R
b10 '"
b10000100000 N
b1010 O
b111000 W
b111000 @"
b111000 I"
b1001 P
b100000011001111111111111110111 d
b100000011001111111111111110111 8"
b100000011001111111111111110111 H"
bx $
bx )
bx -
bx 1
bx U
bx h
bx *"
bx <"
b111000 f
b111000 |
b111000 ""
b111000 ,"
b111000 G"
1'
#81
b1100 ^
b1100 %"
b1100 5"
#85
0'
#90
x0
bx r
bx q
bx X
bx m
bx t
bx y
bx +"
b0x000 l
b0x000 x
bx e
bx k
bx {
bx !"
bx n
bx u
bx s
b1000 Y
b1000 o
b1000 v
b1000 z
b1000 2"
12
0<
b0 ;
b0 D
b0 L
b0 R
b0 '"
b100000000000 N
b0 O
b1100 W
b1100 @"
b1100 I"
b1100 f
b1100 |
b1100 ""
b1100 ,"
b1100 G"
b1010 P
1'
#91
bx ^
bx %"
bx 5"
#95
0'
#100
00
b0 l
b0 x
b1100 e
b1100 k
b1100 {
b1100 !"
b0 r
b1100 n
b1100 u
b1100 s
b100 q
b100 X
b100 m
b100 t
b100 y
b100 +"
15
1?
18
02
b1 ;
b1 D
b1 L
b1 R
b1 '"
b101000000010000 N
b1 O
b1100 \
b1100 9"
b1100 A"
bx W
bx @"
bx I"
b0 P
bx f
bx |
bx ""
bx ,"
bx G"
1'
#101
b1100 ^
b1100 %"
b1100 5"
#105
0'
