Singlecycle/mipsmen.v
module dmem(input  wire clk, we,
            input  wire[31:0] a, wd,
            output [31:0] rd);

  reg [31:0] RAM[0:63];

  assign rd = RAM[a[31:2]]; // word aligned

  always @(posedge clk)
  begin
    if (we)
      RAM[a[31:2]] <= wd;
  end    
endmodule


module imem(input [5:0]  a,
            output [31:0] rd);

  reg [31:0] RAM[0:63];

  initial
    begin
    	$readmemh("memfile.dat", RAM);
      	//("memfile.dat",RAM); // initialize memory
    end

  assign rd = RAM[a]; // word aligned
endmodule

Singlecycle/LOGIC.v
module Logic (A,B,AluOp,Logic);
  input [31:0] A,B;
  input [3:0] AluOp;
  output [31:0] Logic;

  assign Logic = AluOp[1]? AluOp[0]? ~(A | B) 
                                      : 
                                     (A ^ B) // cuando el Alu[1] es 1 haremos un xor o un nor 
                            :   
                           AluOp[0]? (A | B) 
                                      : 
                                     (A & B); /// cuando el Alu[0] es 0 haremos un and o un Or

endmodule

Multicycle/ARITMETIC.v
module Aritmetic (AluOp,A,B,Aritm);
  input [3:0] AluOp;
  input [31:0] A,B;
  output [31:0] Aritm;
  wire [31:0] mux1,adder,extend,mux2;

// mux b con ~b depedende del AluOp[1] determina si es suma o resta 
  assign mux1 = AluOp[1]? ~B : B;

// suma el AluOp[1] con A y B si es suma y con ~B si es resta
  assign adder = AluOp[1] + A + mux1;

// sacamos el bit mas significativo del adder y hacer el extend 
  assign extend = adder[31] + 32'b0;  // = 0 v 1 se llena solo al ser de 32 bits if 0: 000....00000 ^ 1: 0000000... 01

// mux para determinar si se pide un slt o no y asu vez dar la salida del bloque de AritmeticOp
  assign Aritm = AluOp[3]? extend : adder;
endmodule

Multicycle/ALU.v
module Alu (A,B,AluOp,Result,zero);
  input [31:0] A,B;
  input [3:0] AluOp;
  output [31:0] Result;
  output zero;
  wire [31:0] Logic,Aritm;

  //Modulo Aritmetic aqui se hace el add , sub y slt 
  Aritmetic Arit (.A(A),
               .B(B),
               .AluOp(AluOp),
               .Aritm(Aritm)
               );

  //Modulo Logic aqui se hace el and, or, nor, xor 
  Logic Log (.A(A),
           .B(B),
           .AluOp(AluOp),
           .Logic(Logic)
           );

  // El Result depende de del segundo bit mas significativo si es 0 sabemos que ejecutaremos el modulo Aritmetic pero sino ejecutaremos el modulo Logic 
  assign Result = AluOp[2]? Logic : Aritm;
  
  //El zero se prende cuando todos los digitos del result son ceros y para asegurarnos de eso hacemos un or entre todos los bits del Result 
  //se niega porque el or entre todos los bits del Result si todos son ceros seria 0 y queremos q la salida sea 1 .
  assign zero = ~(| Result);

endmodule

Singlecycle/mips.v
// Updated to SystemVerilog - Harris Harris version
// Single-cycle MIPS processor
//--------------------------------------------------------------

// files needed for simulation:
//  mipsttest.v
//  mipstop.v
//  mipsmem.v
//  mips.v
//  mipsparts.v

// single-cycle MIPS processor
module mips(input          clk, reset,
            output  [31:0] pc, 
            input   [31:0] instr,
            output         memwrite,
            output  [31:0] aluout, writedata,
            input   [31:0] readdata);

  wire        memtoreg, branch,
               pcsrc, zero,
               alusrc, regdst, regwrite, jump;

 wire [3:0]  alucontrol;

  controller c(instr[31:26], instr[5:0], zero,
               memtoreg, memwrite, pcsrc,
               alusrc, regdst, regwrite, jump,
               alucontrol);
  datapath dp(clk, reset, memtoreg, pcsrc,
              alusrc, regdst, regwrite, jump,
              alucontrol,
              zero, pc, instr,
              aluout, writedata, readdata);
endmodule

module controller(input   [5:0] op, funct,
                  input         zero,
                  output        memtoreg, memwrite,
                  output        pcsrc, alusrc,
                  output        regdst, regwrite,
                  output        jump,
                  output  [3:0] alucontrol);
  wire [1:0] aluop;
  wire       branch;

  maindec md(op, memtoreg, memwrite, branch,
             alusrc, regdst, regwrite, jump,
             aluop);
  aludec  ad(funct, aluop, alucontrol);

  assign pcsrc = branch & ((op == 6'b000101)? ~zero : zero);
endmodule

module maindec(input   [5:0] op,
               output        memtoreg, memwrite,
               output        branch, alusrc,
               output        regdst, regwrite,
               output        jump,
               output  [1:0] aluop);

  reg [8:0] controls;

  assign {regwrite, regdst, alusrc,
          branch, memwrite,
          memtoreg, jump, aluop} = controls;

always @* begin
    case(op)
      6'b000000: controls <= 9'b110000010; //Rtype
      6'b100011: controls <= 9'b101001000; //LW
      6'b101011: controls <= 9'b001010000; //SW
      6'b000100: controls <= 9'b000100001; //BEQ
      6'b000101: controls <= 9'b000100001; //BNE
      6'b001000: controls <= 9'b101000000; //ADDI
      6'b000010: controls <= 9'b000000100; //J
      6'b001101: controls <= 9'b101000011; //ORI
      default:   controls <= 9'bxxxxxxxxx; //???
    endcase
  end
endmodule

module aludec(input   [5:0] funct,
              input   [1:0] aluop,
              output reg [3:0] alucontrol);

  always @* begin
    case(aluop)
      2'b00: alucontrol <= 4'b0000;  // add
      2'b01: alucontrol <= 4'b0010;  // sub
      2'b11: alucontrol <= 4'b0101;  // or

      default: case(funct)          // RTYPE
          6'b100000: alucontrol <= 4'b0000; // ADD
          6'b100010: alucontrol <= 4'b0010; // SUB
          6'b100100: alucontrol <= 4'b0100; // AND
          6'b100101: alucontrol <= 4'b0101; // OR
          6'b100111: alucontrol <= 4'b0111; // NOR
          6'b100110: alucontrol <= 4'b0110; // XOR
          6'b101010: alucontrol <= 4'b1010; // SLT
          default:   alucontrol <= 4'bxxxx; // ???
      endcase
    endcase
  end
endmodule
module datapath(input          clk, reset,
                input          memtoreg, pcsrc,
                input          alusrc, regdst,
                input          regwrite, jump,
                input   [3:0]  alucontrol,
                output         zero,
                output  [31:0] pc,
                input   [31:0] instr,
                output  [31:0] aluout, writedata,
                input   [31:0] readdata);

  wire [4:0]  writereg;
  wire [31:0] pcnext, pcnextbr, pcplus4, pcbranch;
  wire [31:0] signimm, signimmsh;
  wire [31:0] srca, srcb;
  wire [31:0] result;
// next PC logic
  flopr #(32) pcreg(clk, reset, pcnext, pc);
  adder       pcadd1(pc, 32'b100, pcplus4);
  sl2         immsh(signimm, signimmsh);
  adder       pcadd2(pcplus4, signimmsh, pcbranch);
  mux2 #(32)  pcbrmux(pcplus4, pcbranch, pcsrc,
                      pcnextbr);
  mux2 #(32)  pcmux(pcnextbr, {pcplus4[31:28],
                    instr[25:0], 2'b00},
                    jump, pcnext);

  // register file logic
  regfile     rf(clk, regwrite, instr[25:21],
                 instr[20:16], writereg,
                 result, srca, writedata);
  mux2 #(5)   wrmux(instr[20:16], instr[15:11],
                    regdst, writereg);
  mux2 #(32)  resmux(aluout, readdata,
                     memtoreg, result);
  signext     se(instr[15:0], alusrc, alucontrol, signimm);

  // ALU logic
  mux2 #(32)  srcbmux(writedata, signimm, alusrc,
                      srcb);
  Alu         alu(.A(srca), .B(srcb), .AluOp(alucontrol),
                  .Result(aluout), .zero(zero));

endmodule

Singlecycle/mipstop.v
//------------------------------------------------
// top.v
// Updated to SystemVerilog - Harris Harris version
// Top level system including MIPS and memories
//------------------------------------------------

module top(input         clk, reset, 
           output [31:0] writedata, dataadr, 
           output        memwrite);

  wire [31:0] pc, instr, readdata;
  
  // instantiate processor and memories
  mips mips(clk, reset, pc, instr, memwrite, dataadr, writedata, readdata);
  imem imem(pc[7:2], instr);
  dmem dmem(clk, memwrite, dataadr, writedata, readdata);

endmodule

Multicycle/mipstest.v
module testbench();
  reg clk;
  reg reset;

  wire [31:0]writedata, adr;
  wire memwrite;

  // instantiate device to be tested
  top dut(clk, reset, writedata, adr, memwrite);
  //dut dut(clk, reset, writedata, dataadr, memwrite);

  // initialize test
  initial
    begin
      reset <= 1; 
      #22; 
      reset <= 0;
    end

  // generate clock to sequence tests
  always
    begin
      clk <= 1; 
      #5; 
      clk <= 0; 
      #5;
    end

  // check that 7 gets written to address 84
  always@(negedge clk)
    begin
      if(memwrite) begin
        if(adr === 80 && writedata === 7) begin
          $display("Simulation succeeded");
          $finish;
        end else if (adr !== 80) begin
          $display("Simulation failed");
          $finish;
        end
      end
    end

    initial begin
        $dumpfile("testbenchmulti.vcd");
        $dumpvars; 
    end

endmodule

Singlecycle/mipsparts.v
//------------------------------------------------
// mipsparts.sv
// Updated to SystemVerilog - Harris Harris version
// Components used in MIPS processor
//------------------------------------------------

module regfile(input          clk, 
               input          we3, 
               input   [4:0]  ra1, ra2, wa3, 
               input   [31:0] wd3, 
               output  [31:0] rd1, rd2);

  reg [31:0] rf[31:0];

  // three ported register file
  // read two ports combinationally
  // write third port on rising edge of clock
  // register 0 hardwired to 0


  always @(posedge clk) begin
    if (we3) rf[wa3] <= wd3;    
  end
  assign rd1 = (ra1 != 0) ? rf[ra1] : 0;
  assign rd2 = (ra2 != 0) ? rf[ra2] : 0;
endmodule

module adder(input   [31:0] a, b,
             output  [31:0] y);

  assign y = a + b;
endmodule

module sl2(input   [31:0] a,
           output  [31:0] y);

  // shift left by 2
  assign y = {a[29:0], 2'b00};
endmodule
module signext(input   [15:0] a,
               input   alusrc,
               input   [3:0]alucontrol,
               output  [31:0] y);
  assign y = (alucontrol== 4'b0101 && alusrc == 1'b1 )? {{16{1'b0}},a}:{{16{a[15]}}, a};
//  assign y = {{16{a[15]}}, a};
endmodule

module flopr #(parameter WIDTH = 8)
              (input               clk, reset,
               input   [WIDTH-1:0] d,
               output reg [WIDTH-1:0] q);

  always @(posedge clk, posedge reset) begin
    if (reset) q <= 0;
    else       q <= d;
  end
endmodule

module flopenr #(parameter WIDTH = 8)
                (input               clk, reset,
                 input               en,
                 input   [WIDTH-1:0] d,
                 output reg [WIDTH-1:0] q);

  always @(posedge clk, posedge reset) begin
    if      (reset) q <= 0;
    else if (en)    q <= d;
  end
endmodule

module mux2 #(parameter WIDTH = 8)
             (input   [WIDTH-1:0] d0, d1,
              input               s,
              output  [WIDTH-1:0] y);

  assign y = s ? d1 : d0;
endmodule

Singlecycle/testbench.vcd
$date
	Tue Jul 21 04:46:20 2020
$end
$version
	Icarus Verilog
$end
$timescale
	1s
$end
$scope module flopenr $end
$var wire 1 ! clk $end
$var wire 8 " d [7:0] $end
$var wire 1 # en $end
$var wire 1 $ reset $end
$var reg 8 % q [7:0] $end
$upscope $end
$scope module testbench $end
$var wire 32 & writedata [31:0] $end
$var wire 1 ' memwrite $end
$var wire 32 ( adr [31:0] $end
$var reg 1 ) clk $end
$var reg 1 * reset $end
$scope module dut $end
$var wire 1 ) clk $end
$var wire 1 * reset $end
$var wire 32 + writedata [31:0] $end
$var wire 32 , readdata [31:0] $end
$var wire 32 - pc [31:0] $end
$var wire 1 ' memwrite $end
$var wire 32 . instr [31:0] $end
$var wire 32 / dataadr [31:0] $end
$scope module dmem $end
$var wire 1 ) clk $end
$var wire 32 0 rd [31:0] $end
$var wire 1 ' we $end
$var wire 32 1 wd [31:0] $end
$var wire 32 2 a [31:0] $end
$upscope $end
$scope module imem $end
$var wire 6 3 a [5:0] $end
$var wire 32 4 rd [31:0] $end
$upscope $end
$scope module mips $end
$var wire 1 ) clk $end
$var wire 32 5 instr [31:0] $end
$var wire 32 6 readdata [31:0] $end
$var wire 1 * reset $end
$var wire 1 7 zero $end
$var wire 32 8 writedata [31:0] $end
$var wire 1 9 regwrite $end
$var wire 1 : regdst $end
$var wire 1 ; pcsrc $end
$var wire 32 < pc [31:0] $end
$var wire 1 ' memwrite $end
$var wire 1 = memtoreg $end
$var wire 1 > jump $end
$var wire 1 ? alusrc $end
$var wire 32 @ aluout [31:0] $end
$var wire 4 A alucontrol [3:0] $end
$scope module c $end
$var wire 6 B funct [5:0] $end
$var wire 6 C op [5:0] $end
$var wire 1 ; pcsrc $end
$var wire 1 7 zero $end
$var wire 1 9 regwrite $end
$var wire 1 : regdst $end
$var wire 1 ' memwrite $end
$var wire 1 = memtoreg $end
$var wire 1 > jump $end
$var wire 1 D branch $end
$var wire 1 ? alusrc $end
$var wire 2 E aluop [1:0] $end
$var wire 4 F alucontrol [3:0] $end
$scope module ad $end
$var wire 6 G funct [5:0] $end
$var wire 2 H aluop [1:0] $end
$var reg 4 I alucontrol [3:0] $end
$upscope $end
$scope module md $end
$var wire 6 J op [5:0] $end
$var wire 1 9 regwrite $end
$var wire 1 : regdst $end
$var wire 1 ' memwrite $end
$var wire 1 = memtoreg $end
$var wire 1 > jump $end
$var wire 1 D branch $end
$var wire 1 ? alusrc $end
$var wire 2 K aluop [1:0] $end
$var reg 9 L controls [8:0] $end
$upscope $end
$upscope $end
$scope module dp $end
$var wire 4 M alucontrol [3:0] $end
$var wire 1 ? alusrc $end
$var wire 1 ) clk $end
$var wire 32 N instr [31:0] $end
$var wire 1 > jump $end
$var wire 1 = memtoreg $end
$var wire 1 ; pcsrc $end
$var wire 32 O readdata [31:0] $end
$var wire 1 : regdst $end
$var wire 1 9 regwrite $end
$var wire 1 * reset $end
$var wire 1 7 zero $end
$var wire 5 P writereg [4:0] $end
$var wire 32 Q writedata [31:0] $end
$var wire 32 R srcb [31:0] $end
$var wire 32 S srca [31:0] $end
$var wire 32 T signimmsh [31:0] $end
$var wire 32 U signimm [31:0] $end
$var wire 32 V result [31:0] $end
$var wire 32 W pcplus4 [31:0] $end
$var wire 32 X pcnextbr [31:0] $end
$var wire 32 Y pcnext [31:0] $end
$var wire 32 Z pcbranch [31:0] $end
$var wire 32 [ pc [31:0] $end
$var wire 32 \ aluout [31:0] $end
$scope module alu $end
$var wire 4 ] AluOp [3:0] $end
$var wire 1 7 zero $end
$var wire 32 ^ Result [31:0] $end
$var wire 32 _ Logic [31:0] $end
$var wire 32 ` B [31:0] $end
$var wire 32 a Aritm [31:0] $end
$var wire 32 b A [31:0] $end
$scope module Arit $end
$var wire 4 c AluOp [3:0] $end
$var wire 32 d mux1 [31:0] $end
$var wire 32 e extend [31:0] $end
$var wire 32 f adder [31:0] $end
$var wire 32 g B [31:0] $end
$var wire 32 h Aritm [31:0] $end
$var wire 32 i A [31:0] $end
$upscope $end
$scope module Log $end
$var wire 4 j AluOp [3:0] $end
$var wire 32 k Logic [31:0] $end
$var wire 32 l B [31:0] $end
$var wire 32 m A [31:0] $end
$upscope $end
$upscope $end
$scope module immsh $end
$var wire 32 n y [31:0] $end
$var wire 32 o a [31:0] $end
$upscope $end
$scope module pcadd1 $end
$var wire 32 p b [31:0] $end
$var wire 32 q y [31:0] $end
$var wire 32 r a [31:0] $end
$upscope $end
$scope module pcadd2 $end
$var wire 32 s a [31:0] $end
$var wire 32 t b [31:0] $end
$var wire 32 u y [31:0] $end
$upscope $end
$scope module pcbrmux $end
$var wire 32 v d0 [31:0] $end
$var wire 32 w d1 [31:0] $end
$var wire 1 ; s $end
$var wire 32 x y [31:0] $end
$upscope $end
$scope module pcmux $end
$var wire 32 y d0 [31:0] $end
$var wire 32 z d1 [31:0] $end
$var wire 1 > s $end
$var wire 32 { y [31:0] $end
$upscope $end
$scope module pcreg $end
$var wire 1 ) clk $end
$var wire 32 | d [31:0] $end
$var wire 1 * reset $end
$var reg 32 } q [31:0] $end
$upscope $end
$scope module resmux $end
$var wire 32 ~ d0 [31:0] $end
$var wire 32 !" d1 [31:0] $end
$var wire 1 = s $end
$var wire 32 "" y [31:0] $end
$upscope $end
$scope module rf $end
$var wire 1 ) clk $end
$var wire 5 #" ra1 [4:0] $end
$var wire 5 $" ra2 [4:0] $end
$var wire 32 %" wd3 [31:0] $end
$var wire 1 9 we3 $end
$var wire 5 &" wa3 [4:0] $end
$var wire 32 '" rd2 [31:0] $end
$var wire 32 (" rd1 [31:0] $end
$upscope $end
$scope module se $end
$var wire 16 )" a [15:0] $end
$var wire 4 *" alucontrol [3:0] $end
$var wire 1 ? alusrc $end
$var wire 32 +" y [31:0] $end
$upscope $end
$scope module srcbmux $end
$var wire 32 ," d0 [31:0] $end
$var wire 32 -" d1 [31:0] $end
$var wire 1 ? s $end
$var wire 32 ." y [31:0] $end
$upscope $end
$scope module wrmux $end
$var wire 5 /" d0 [4:0] $end
$var wire 5 0" d1 [4:0] $end
$var wire 1 : s $end
$var wire 5 1" y [4:0] $end
$upscope $end
$upscope $end
$upscope $end
$upscope $end
$upscope $end
$enddefinitions $end
#0
$dumpvars
b10 1"
b0 0"
b10 /"
b101 ."
b101 -"
bx ,"
b101 +"
b0 *"
b101 )"
b0 ("
bx '"
b10 &"
b101 %"
b10 $"
b0 #"
b101 ""
bx !"
b101 ~
b0 }
b100 |
b100 {
b10000000000000010100 z
b100 y
b100 x
b11000 w
b100 v
b11000 u
b10100 t
b100 s
b0 r
b100 q
b100 p
b101 o
b10100 n
b0 m
b101 l
b0 k
b0 j
b0 i
b101 h
b101 g
b101 f
b0 e
b101 d
b0 c
b0 b
b101 a
b101 `
b0 _
b101 ^
b0 ]
b101 \
b0 [
b11000 Z
b100 Y
b100 X
b100 W
b101 V
b101 U
b10100 T
b0 S
b101 R
bx Q
b10 P
bx O
b100000000000100000000000000101 N
b0 M
b101000000 L
b0 K
b1000 J
b0 I
b0 H
b101 G
b0 F
b0 E
0D
b1000 C
b101 B
b0 A
b101 @
1?
0>
0=
b0 <
0;
0:
19
bx 8
07
bx 6
b100000000000100000000000000101 5
b100000000000100000000000000101 4
b0 3
b101 2
bx 1
bx 0
b101 /
b100000000000100000000000000101 .
b0 -
bx ,
bx +
1*
1)
b101 (
0'
bx &
bx %
z$
z#
bz "
z!
$end
#5
0)
#10
b101 &
b101 +
b101 1
b101 8
b101 Q
b101 '"
b101 ,"
1)
#15
0)
#20
1)
#22
0*
#25
0)
#30
b1100 V
b1100 ""
b1100 %"
b1100 (
b1100 /
b1100 2
b1100 @
b1100 \
b1100 ^
b1100 ~
b1100 a
b1100 h
b1100 f
b1100 d
b1100 R
b1100 `
b1100 g
b1100 l
b1100 ."
b110000 T
b110000 n
b110000 t
bx &
bx +
bx 1
bx 8
bx Q
bx '"
bx ,"
b11 P
b11 &"
b11 1"
b1100 U
b1100 o
b1100 +"
b1100 -"
b1000 Y
b1000 {
b1000 |
b1100 B
b1100 G
b11000000000000110000 z
b11 $"
b11 /"
b1100 )"
b1000 X
b1000 x
b1000 y
b100000000000110000000000001100 .
b100000000000110000000000001100 4
b100000000000110000000000001100 5
b100000000000110000000000001100 N
b1 3
b111000 Z
b111000 u
b111000 w
b1000 W
b1000 q
b1000 s
b1000 v
b100 -
b100 <
b100 [
b100 r
b100 }
1)
#35
0)
#40
b100 _
b100 k
b11 V
b11 ""
b11 %"
b11 (
b11 /
b11 2
b11 @
b11 \
b11 ^
b11 ~
b11111111111111111111111111110111 d
b11 a
b11 h
b11111111111111111111111111110111 R
b11111111111111111111111111110111 `
b11111111111111111111111111110111 g
b11111111111111111111111111110111 l
b11111111111111111111111111110111 ."
b11111111111111111111111111011100 T
b11111111111111111111111111011100 n
b11111111111111111111111111011100 t
b11 f
b1100 S
b1100 b
b1100 i
b1100 m
b1100 ("
b111 P
b111 &"
b111 1"
b11111111111111111111111111110111 U
b11111111111111111111111111110111 o
b11111111111111111111111111110111 +"
b11111111111111111111111111110111 -"
b1100 Y
b1100 {
b1100 |
b110111 B
b110111 G
b1100111111111111111011100 z
b11 #"
b111 $"
b111 /"
b11111 0"
b1111111111110111 )"
bx &
bx +
bx 1
bx 8
bx Q
bx '"
bx ,"
b1100 X
b1100 x
b1100 y
b100000011001111111111111110111 .
b100000011001111111111111110111 4
b100000011001111111111111110111 5
b100000011001111111111111110111 N
b10 3
b11111111111111111111111111101000 Z
b11111111111111111111111111101000 u
b11111111111111111111111111101000 w
b1100 W
b1100 q
b1100 s
b1100 v
b1000 -
b1000 <
b1000 [
b1000 r
b1000 }
1)
#45
0)
#50
b101 A
b101 F
b101 I
b101 M
b101 ]
b101 c
b101 j
b101 *"
1:
0?
b10 E
b10 H
b10 K
b110000010 L
b111 _
b111 k
b111 V
b111 ""
b111 %"
b111 (
b111 /
b111 2
b111 @
b111 \
b111 ^
b111 ~
b101 d
b0 e
b1000 a
b1000 h
b101 R
b101 `
b101 g
b101 l
b101 ."
b1000000010010100 T
b1000000010010100 n
b1000000010010100 t
b1000 f
b11 S
b11 b
b11 i
b11 m
b11 ("
b100 P
b100 &"
b100 1"
b10000000100101 U
b10000000100101 o
b10000000100101 +"
b10000000100101 -"
b10000 Y
b10000 {
b10000 |
b0 C
b0 J
b100101 B
b100101 G
b11100010001000000010010100 z
b111 #"
b10 $"
b10 /"
b100 0"
b10000000100101 )"
b101 &
b101 +
b101 1
b101 8
b101 Q
b101 '"
b101 ,"
b10000 X
b10000 x
b10000 y
b111000100010000000100101 .
b111000100010000000100101 4
b111000100010000000100101 5
b111000100010000000100101 N
b11 3
b1000000010100100 Z
b1000000010100100 u
b1000000010100100 w
b10000 W
b10000 q
b10000 s
b10000 v
b1100 -
b1100 <
b1100 [
b1100 r
b1100 }
1)
#55
0)
#60
b100 A
b100 F
b100 I
b100 M
b100 ]
b100 c
b100 j
b100 *"
b100 V
b100 ""
b100 %"
b100 (
b100 /
b100 2
b100 @
b100 \
b100 ^
b100 ~
b100 _
b100 k
b111 d
b10011 a
b10011 h
b111 R
b111 `
b111 g
b111 l
b111 ."
b1010000010010000 T
b1010000010010000 n
b1010000010010000 t
b10011 f
b1100 S
b1100 b
b1100 i
b1100 m
b1100 ("
b111 &
b111 +
b111 1
b111 8
b111 Q
b111 '"
b111 ,"
b101 P
b101 &"
b101 1"
b10100000100100 U
b10100000100100 o
b10100000100100 +"
b10100000100100 -"
b10100 Y
b10100 {
b10100 |
b100100 B
b100100 G
b1100100001010000010010000 z
b11 #"
b100 $"
b100 /"
b101 0"
b10100000100100 )"
b10100 X
b10100 x
b10100 y
b11001000010100000100100 .
b11001000010100000100100 4
b11001000010100000100100 5
b11001000010100000100100 N
b100 3
b1010000010100100 Z
b1010000010100100 u
b1010000010100100 w
b10100 W
b10100 q
b10100 s
b10100 v
b10000 -
b10000 <
b10000 [
b10000 r
b10000 }
1)
#65
0)
#70
b1011 V
b1011 ""
b1011 %"
b1011 (
b1011 /
b1011 2
b1011 @
b1011 \
b1011 ^
b1011 ~
b0 A
b0 F
b0 I
b0 M
b0 ]
b0 c
b0 j
b0 *"
b1011 a
b1011 h
b1010000010000000 T
b1010000010000000 n
b1010000010000000 t
b1011 f
b100 S
b100 b
b100 i
b100 m
b100 ("
b10100000100000 U
b10100000100000 o
b10100000100000 +"
b10100000100000 -"
b11000 Y
b11000 {
b11000 |
b100000 B
b100000 G
b10100100001010000010000000 z
b101 #"
b10100000100000 )"
b11000 X
b11000 x
b11000 y
b101001000010100000100000 .
b101001000010100000100000 4
b101001000010100000100000 5
b101001000010100000100000 N
b101 3
b1010000010011000 Z
b1010000010011000 u
b1010000010011000 w
b11000 W
b11000 q
b11000 s
b11000 v
b10100 -
b10100 <
b10100 [
b10100 r
b10100 }
1)
#75
0)
#80
0;
07
b0 e
09
0:
1D
b1 E
b1 H
b1 K
b100001 L
b10 A
b10 F
b10 I
b10 M
b10 ]
b10 c
b10 j
b10 *"
b11111111111111111111111111111100 d
b1000 _
b1000 k
b1000 V
b1000 ""
b1000 %"
b11 R
b11 `
b11 g
b11 l
b11 ."
b101000 T
b101000 n
b101000 t
b1000 (
b1000 /
b1000 2
b1000 @
b1000 \
b1000 ^
b1000 ~
b11 &
b11 +
b11 1
b11 8
b11 Q
b11 '"
b11 ,"
b111 P
b111 &"
b111 1"
b1010 U
b1010 o
b1010 +"
b1010 -"
b1000 a
b1000 h
b11100 Y
b11100 {
b11100 |
b100 C
b100 J
b1010 B
b1010 G
b10100111000000000000101000 z
b111 $"
b111 /"
b0 0"
b1010 )"
b1000 f
b1011 S
b1011 b
b1011 i
b1011 m
b1011 ("
b11100 X
b11100 x
b11100 y
b10000101001110000000000001010 .
b10000101001110000000000001010 4
b10000101001110000000000001010 5
b10000101001110000000000001010 N
b110 3
b1000100 Z
b1000100 u
b1000100 w
b11100 W
b11100 q
b11100 s
b11100 v
b11000 -
b11000 <
b11000 [
b11000 r
b11000 }
1)
#85
0)
#90
17
b1010 A
b1010 F
b1010 I
b1010 M
b1010 ]
b1010 c
b1010 j
b1010 *"
19
1:
0D
b10 E
b10 H
b10 K
b110000010 L
b1011 _
b1011 k
b0 V
b0 ""
b0 %"
b11111111111111111111111111111000 d
b0 (
b0 /
b0 2
b0 @
b0 \
b0 ^
b0 ~
b0 a
b0 h
b111 R
b111 `
b111 g
b111 l
b111 ."
b1000000010101000 T
b1000000010101000 n
b1000000010101000 t
b101 f
b1100 S
b1100 b
b1100 i
b1100 m
b1100 ("
b111 &
b111 +
b111 1
b111 8
b111 Q
b111 '"
b111 ,"
b100 P
b100 &"
b100 1"
b10000000101010 U
b10000000101010 o
b10000000101010 +"
b10000000101010 -"
b100000 Y
b100000 {
b100000 |
b0 C
b0 J
b101010 B
b101010 G
b1100100001000000010101000 z
b11 #"
b100 $"
b100 /"
b100 0"
b10000000101010 )"
b100000 X
b100000 x
b100000 y
b11001000010000000101010 .
b11001000010000000101010 4
b11001000010000000101010 5
b11001000010000000101010 N
b111 3
b1000000011001000 Z
b1000000011001000 u
b1000000011001000 w
b100000 W
b100000 q
b100000 s
b100000 v
b11100 -
b11100 <
b11100 [
b11100 r
b11100 }
1)
#95
0)
#100
1;
09
0:
1D
b1 E
b1 H
b1 K
b100001 L
b10 A
b10 F
b10 I
b10 M
b10 ]
b10 c
b10 j
b10 *"
17
b0 V
b0 ""
b0 %"
b0 (
b0 /
b0 2
b0 @
b0 \
b0 ^
b0 ~
b0 _
b0 k
b0 a
b0 h
b11111111111111111111111111111111 d
b0 e
b100 T
b100 n
b100 t
b0 f
b0 S
b0 b
b0 i
b0 m
b0 ("
b0 P
b0 &"
b0 1"
b1 U
b1 o
b1 +"
b1 -"
b0 R
b0 `
b0 g
b0 l
b0 ."
b101000 Y
b101000 {
b101000 |
b100 C
b100 J
b1 B
b1 G
b10000000000000000000000100 z
b100 #"
b0 $"
b0 /"
b0 0"
b1 )"
b0 &
b0 +
b0 1
b0 8
b0 Q
b0 '"
b0 ,"
b101000 X
b101000 x
b101000 y
b10000100000000000000000000001 .
b10000100000000000000000000001 4
b10000100000000000000000000001 5
b10000100000000000000000000001 N
b1000 3
b101000 Z
b101000 u
b101000 w
b100100 W
b100100 q
b100100 s
b100100 v
b100000 -
b100000 <
b100000 [
b100000 r
b100000 }
1)
#105
0)
#110
b1010 A
b1010 F
b1010 I
b1010 M
b1010 ]
b1010 c
b1010 j
b1010 *"
19
1:
0D
b10 E
b10 H
b10 K
b110000010 L
0;
b1 e
b110 _
b110 k
07
b1 V
b1 ""
b1 %"
b11111111111111111111111111111010 d
b1 (
b1 /
b1 2
b1 @
b1 \
b1 ^
b1 ~
b1 a
b1 h
b101 R
b101 `
b101 g
b101 l
b101 ."
b1000000010101000 T
b1000000010101000 n
b1000000010101000 t
b11111111111111111111111111111110 f
b11 S
b11 b
b11 i
b11 m
b11 ("
b101 &
b101 +
b101 1
b101 8
b101 Q
b101 '"
b101 ,"
b100 P
b100 &"
b100 1"
b10000000101010 U
b10000000101010 o
b10000000101010 +"
b10000000101010 -"
b101100 Y
b101100 {
b101100 |
b0 C
b0 J
b101010 B
b101010 G
b11100010001000000010101000 z
b111 #"
b10 $"
b10 /"
b100 0"
b10000000101010 )"
b101100 X
b101100 x
b101100 y
b111000100010000000101010 .
b111000100010000000101010 4
b111000100010000000101010 5
b111000100010000000101010 N
b1010 3
b1000000011010100 Z
b1000000011010100 u
b1000000011010100 w
b101100 W
b101100 q
b101100 s
b101100 v
b101000 -
b101000 <
b101000 [
b101000 r
b101000 }
1)
#115
0)
#120
b1100 V
b1100 ""
b1100 %"
b0 e
b1100 (
b1100 /
b1100 2
b1100 @
b1100 \
b1100 ^
b1100 ~
b1100 a
b1100 h
b0 A
b0 F
b0 I
b0 M
b0 ]
b0 c
b0 j
b0 *"
b1 _
b1 k
b1011 d
b1011 R
b1011 `
b1011 g
b1011 l
b1011 ."
b1110000010000000 T
b1110000010000000 n
b1110000010000000 t
b1100 f
b1 S
b1 b
b1 i
b1 m
b1 ("
b1011 &
b1011 +
b1011 1
b1011 8
b1011 Q
b1011 '"
b1011 ,"
b111 P
b111 &"
b111 1"
b11100000100000 U
b11100000100000 o
b11100000100000 +"
b11100000100000 -"
b110000 Y
b110000 {
b110000 |
b100000 B
b100000 G
b10000101001110000010000000 z
b100 #"
b101 $"
b101 /"
b111 0"
b11100000100000 )"
b110000 X
b110000 x
b110000 y
b100001010011100000100000 .
b100001010011100000100000 4
b100001010011100000100000 5
b100001010011100000100000 N
b1011 3
b1110000010110000 Z
b1110000010110000 u
b1110000010110000 w
b110000 W
b110000 q
b110000 s
b110000 v
b101100 -
b101100 <
b101100 [
b101100 r
b101100 }
1)
#125
0)
#130
b10 A
b10 F
b10 I
b10 M
b10 ]
b10 c
b10 j
b10 *"
b1001 _
b1001 k
b111 V
b111 ""
b111 %"
b111 (
b111 /
b111 2
b111 @
b111 \
b111 ^
b111 ~
b11111111111111111111111111111010 d
b111 a
b111 h
b101 R
b101 `
b101 g
b101 l
b101 ."
b1110000010001000 T
b1110000010001000 n
b1110000010001000 t
b111 f
b1100 S
b1100 b
b1100 i
b1100 m
b1100 ("
b101 &
b101 +
b101 1
b101 8
b101 Q
b101 '"
b101 ,"
b11100000100010 U
b11100000100010 o
b11100000100010 +"
b11100000100010 -"
b110100 Y
b110100 {
b110100 |
b100010 B
b100010 G
b11100010001110000010001000 z
b111 #"
b10 $"
b10 /"
b11100000100010 )"
b110100 X
b110100 x
b110100 y
b111000100011100000100010 .
b111000100011100000100010 4
b111000100011100000100010 5
b111000100011100000100010 N
b1100 3
b1110000010111100 Z
b1110000010111100 u
b1110000010111100 w
b110100 W
b110100 q
b110100 s
b110100 v
b110000 -
b110000 <
b110000 [
b110000 r
b110000 }
1)
#135
0)
